__init__.py
mujoco_connector/__init__.py
mujoco_connector/mujoco_plugin/mujoco-3.2.7/libmultiverse_connector.so
mujoco_connector/mujoco_plugin/mujoco-3.2.7/multiverse_connector.dll
mujoco_connector/mujoco_plugin/mujoco-3.3.0/libmultiverse_connector.so
mujoco_connector/mujoco_plugin/mujoco-3.3.0/multiverse_connector.dll
mujoco_connector/mujoco_plugin/mujoco-3.3.1/libmultiverse_connector.so
mujoco_connector/mujoco_plugin/mujoco-3.3.1/multiverse_connector.dll
mujoco_connector/mujoco_plugin/mujoco-3.3.2/libmultiverse_connector.so
mujoco_connector/mujoco_plugin/mujoco-3.3.2/multiverse_connector.dll
mujoco_connector/mujoco_plugin/mujoco-3.3.3/libmultiverse_connector.so
mujoco_connector/mujoco_plugin/mujoco-3.3.3/multiverse_connector.dll
mujoco_connector/mujoco_plugin/mujoco-3.3.4/libmultiverse_connector.so
mujoco_connector/mujoco_plugin/mujoco-3.3.4/multiverse_connector.dll
mujoco_connector/mujoco_plugin/mujoco-3.3.5/libmultiverse_connector.so
mujoco_connector/mujoco_plugin/mujoco-3.3.5/multiverse_connector.dll
mujoco_connector/mujoco_plugin/mujoco-3.3.6/libmultiverse_connector.so
mujoco_connector/mujoco_plugin/mujoco-3.3.6/multiverse_connector.dll
mujoco_connector/mujoco_plugin/mujoco-3.3.7/libmultiverse_connector.so
mujoco_connector/mujoco_plugin/mujoco-3.3.7/multiverse_connector.dll
mujoco_connector/mujoco_plugin/mujoco-3.4.0/libmultiverse_connector.so
mujoco_connector/src/mujoco_connector/__init__.py
mujoco_connector/src/mujoco_connector/mujoco_connector.py
mujoco_connector/src/mujoco_connector/utills.py
multiverse_simulator/__init__.py
multiverse_simulator/multiverse_simulator.py
multiverse_simulator/multiverse_simulator_compiler.py
multiverse_simulator/utils.py
multiverse_simulators-0.0.14.dist-info/licenses/LICENSE
multiverse_simulators-0.0.14.dist-info/METADATA
multiverse_simulators-0.0.14.dist-info/WHEEL
multiverse_simulators-0.0.14.dist-info/top_level.txt
multiverse_simulators-0.0.14.dist-info/RECORD
