Metadata-Version: 2.4
Name: multiverse_simulators
Version: 0.0.14
Summary: A collection of simulators for the Multiverse Framework.
Author-email: Giang Nguyen <hoanggia@uni-bremen.de>
License-Expression: MIT
Project-URL: Homepage, https://github.com/Multiverse-Framework/Multiverse-Simulators-Connector
Project-URL: Bug Tracker, https://github.com/Multiverse-Framework/Multiverse-Simulators-Connector/issues
Classifier: Programming Language :: Python :: 3
Classifier: Operating System :: OS Independent
Requires-Python: >=3.10
License-File: LICENSE
Requires-Dist: mujoco>=3.3.0
Dynamic: license-file
